{
  "統計": {
    "初音ミク": 18,
    "傘村トータ": 17,
    "ヨルシカ": 12,
    "Rap Battle!": 9,
    "梶浦由記": 8,
    "IA": 7,
    "モンスト": 7,
    "金坷垃": 6,
    "GUMI": 6,
    "keeno": 5,
    "Fukase": 5,
    "unknown": 5,
    "結月ゆかり": 4,
    "NEFFEX": 4,
    "Ручной Рептилоид": 4,
    "伍佰 Wu Bai&China Blue": 4,
    "奧華子": 3,
    "Duca": 3,
    "DECO27": 3,
    "绝之望的馬沙": 3,
    "一人一首金坷垃": 3,
    "アフリカンサマータイム": 3,
    "可不": 2,
    "dai": 2,
    "一二三": 2,
    "REOL": 2,
    "宮脇詩音": 2,
    "米津玄師": 2,
    "鏡音リン": 2,
    "解凍三色豆": 2,
    "Beyond": 2,
    "EGOIST": 2,
    "moumoon": 2,
    "Sabaton": 2,
    "佐倉杏子@野中藍": 2,
    "Corn Wave": 2,
    "CaptainMeow": 2,
    "美樹沙耶香@喜多村英梨": 2,
    "MC HotDog 熱狗": 2,
    "НЕБО НАД ГОЛОВОЙ": 2,
    "シド": 1,
    "ツユ": 1,
    "劉醒": 1,
    "林亦": 1,
    "知声": 1,
    "花粥": 1,
    "金莎": 1,
    "阿隆": 1,
    "A路人": 1,
    "Ken": 1,
    "Kra": 1,
    "Дм.": 1,
    "さんひ": 1,
    "全明星": 1,
    "坷杰倫": 1,
    "島谷瞳": 1,
    "張震嶽": 1,
    "桑布伊": 1,
    "殷正洋": 1,
    "洛天依": 1,
    "白冰冰": 1,
    "羅大佑": 1,
    "許冠傑": 1,
    "許冠英": 1,
    "鄭智仁": 1,
    "陳雲山": 1,
    "雨宮天": 1,
    "黃乙玲": 1,
    "黃聖依": 1,
    "黃連煜": 1,
    "ALAN": 1,
    "Ceui": 1,
    "Reol": 1,
    "WI'P": 1,
    "Кино": 1,
    "佐咲紗花": 1,
    "南里侑香": 1,
    "夢乃ゆき": 1,
    "宮村優子": 1,
    "水島周平": 1,
    "澤井美空": 1,
    "猫又小粥": 1,
    "結月そら": 1,
    "茅野愛衣": 1,
    "莉犬くん": 1,
    "菅田将暉": 1,
    "音街ウナ": 1,
    "高橋李依": 1,
    "ANAIT": 1,
    "Cypis": 1,
    "Hanon": 1,
    "iroha": 1,
    "JK小惡魔": 1,
    "kohai": 1,
    "Merak": 1,
    "milet": 1,
    "Ploho": 1,
    "дворы": 1,
    "ぽわぽわP": 1,
    "别惹精神病": 1,
    "天秤ひなみ": 1,
    "安月名莉子": 1,
    "東方萃夢想": 1,
    "植田真梨恵": 1,
    "-inai-": 1,
    "BEYOND": 1,
    "ClariS": 1,
    "HarryP": 1,
    "Metrik": 1,
    "ウォルピス社": 1,
    "ついなちゃん": 1,
    "北大力南逸峰": 1,
    "小鳥遊めぐみ": 1,
    "里奈Rina": 1,
    "Ava Max": 1,
    "Loituma": 1,
    "SadSvit": 1,
    "Synth V": 1,
    "YOASOBI": 1,
    "いきものがかり": 1,
    "ユリイ・カノン": 1,
    "聖地亞戈合唱團": 1,
    "Big Sean": 1,
    "Kalafina": 1,
    "King Gnu": 1,
    "Santiano": 1,
    "TCHaruru": 1,
    "Westlife": 1,
    "АнимациЯ": 1,
    "初音ミクDark": 1,
    "FreeTempo": 1,
    "Mayday五月天": 1,
    "MyGO!!!!!": 1,
    "Synthesia": 1,
    "イヌクワチャンネル": 1,
    "神聖かまってちゃん": 1,
    "Herms Niel": 1,
    "Johann JEG": 1,
    "Juha Rossi": 1,
    "Marshmello": 1,
    "Tom Paxton": 1,
    "初音ミクAppend": 1,
    "Marin Hoxha": 1,
    "Rizky Ayuba": 1,
    "Janne Da Arc": 1,
    "Jeick Abrego": 1,
    "Tymko Padura": 1,
    "Дан. Покрасс": 1,
    "兄弟本色 G.U.T.S": 1,
    "滅火器 Fire EX.": 1,
    "Avril Lavigne": 1,
    "Eino Kettunen": 1,
    "Maksim Mrvica": 1,
    "Secret Garden": 1,
    "Loving Caliber": 1,
    "MY FIRST STORY": 1,
    "strike witches": 1,
    "小飛鼠Amelia Khor": 1,
    "Jean-Marc Natel": 1,
    "楊千嬅 Miriam Yeung": 1,
    "Διονύσιος Σολωμός": 1,
    "美秀集團 Amazing Show": 1,
    "Σταμάτης Σπανουδάκης": 1,
    "Hoffmann von Fallersleben": 1,
    "Ludoviko Lazaro Zamenhofo": 1,
    "Матве́й Исаа́кович Бла́нтер": 1,
    "total": 301
  },
  "占比": {
    "初音ミク": 0.059800664451827246,
    "傘村トータ": 0.05647840531561462,
    "ヨルシカ": 0.03986710963455149,
    "Rap Battle!": 0.029900332225913623,
    "梶浦由記": 0.026578073089700997,
    "IA": 0.023255813953488372,
    "モンスト": 0.023255813953488372,
    "金坷垃": 0.019933554817275746,
    "GUMI": 0.019933554817275746,
    "keeno": 0.016611295681063124,
    "Fukase": 0.016611295681063124,
    "unknown": 0.016611295681063124,
    "結月ゆかり": 0.013289036544850499,
    "NEFFEX": 0.013289036544850499,
    "Ручной Рептилоид": 0.013289036544850499,
    "伍佰 Wu Bai&China Blue": 0.013289036544850499,
    "奧華子": 0.009966777408637873,
    "Duca": 0.009966777408637873,
    "DECO27": 0.009966777408637873,
    "绝之望的馬沙": 0.009966777408637873,
    "一人一首金坷垃": 0.009966777408637873,
    "アフリカンサマータイム": 0.009966777408637873,
    "可不": 0.006644518272425249,
    "dai": 0.006644518272425249,
    "一二三": 0.006644518272425249,
    "REOL": 0.006644518272425249,
    "宮脇詩音": 0.006644518272425249,
    "米津玄師": 0.006644518272425249,
    "鏡音リン": 0.006644518272425249,
    "解凍三色豆": 0.006644518272425249,
    "Beyond": 0.006644518272425249,
    "EGOIST": 0.006644518272425249,
    "moumoon": 0.006644518272425249,
    "Sabaton": 0.006644518272425249,
    "佐倉杏子@野中藍": 0.006644518272425249,
    "Corn Wave": 0.006644518272425249,
    "CaptainMeow": 0.006644518272425249,
    "美樹沙耶香@喜多村英梨": 0.006644518272425249,
    "MC HotDog 熱狗": 0.006644518272425249,
    "НЕБО НАД ГОЛОВОЙ": 0.006644518272425249,
    "シド": 0.0033222591362126247,
    "ツユ": 0.0033222591362126247,
    "劉醒": 0.0033222591362126247,
    "林亦": 0.0033222591362126247,
    "知声": 0.0033222591362126247,
    "花粥": 0.0033222591362126247,
    "金莎": 0.0033222591362126247,
    "阿隆": 0.0033222591362126247,
    "A路人": 0.0033222591362126247,
    "Ken": 0.0033222591362126247,
    "Kra": 0.0033222591362126247,
    "Дм.": 0.0033222591362126247,
    "さんひ": 0.0033222591362126247,
    "全明星": 0.0033222591362126247,
    "坷杰倫": 0.0033222591362126247,
    "島谷瞳": 0.0033222591362126247,
    "張震嶽": 0.0033222591362126247,
    "桑布伊": 0.0033222591362126247,
    "殷正洋": 0.0033222591362126247,
    "洛天依": 0.0033222591362126247,
    "白冰冰": 0.0033222591362126247,
    "羅大佑": 0.0033222591362126247,
    "許冠傑": 0.0033222591362126247,
    "許冠英": 0.0033222591362126247,
    "鄭智仁": 0.0033222591362126247,
    "陳雲山": 0.0033222591362126247,
    "雨宮天": 0.0033222591362126247,
    "黃乙玲": 0.0033222591362126247,
    "黃聖依": 0.0033222591362126247,
    "黃連煜": 0.0033222591362126247,
    "ALAN": 0.0033222591362126247,
    "Ceui": 0.0033222591362126247,
    "Reol": 0.0033222591362126247,
    "WI'P": 0.0033222591362126247,
    "Кино": 0.0033222591362126247,
    "佐咲紗花": 0.0033222591362126247,
    "南里侑香": 0.0033222591362126247,
    "夢乃ゆき": 0.0033222591362126247,
    "宮村優子": 0.0033222591362126247,
    "水島周平": 0.0033222591362126247,
    "澤井美空": 0.0033222591362126247,
    "猫又小粥": 0.0033222591362126247,
    "結月そら": 0.0033222591362126247,
    "茅野愛衣": 0.0033222591362126247,
    "莉犬くん": 0.0033222591362126247,
    "菅田将暉": 0.0033222591362126247,
    "音街ウナ": 0.0033222591362126247,
    "高橋李依": 0.0033222591362126247,
    "ANAIT": 0.0033222591362126247,
    "Cypis": 0.0033222591362126247,
    "Hanon": 0.0033222591362126247,
    "iroha": 0.0033222591362126247,
    "JK小惡魔": 0.0033222591362126247,
    "kohai": 0.0033222591362126247,
    "Merak": 0.0033222591362126247,
    "milet": 0.0033222591362126247,
    "Ploho": 0.0033222591362126247,
    "дворы": 0.0033222591362126247,
    "ぽわぽわP": 0.0033222591362126247,
    "别惹精神病": 0.0033222591362126247,
    "天秤ひなみ": 0.0033222591362126247,
    "安月名莉子": 0.0033222591362126247,
    "東方萃夢想": 0.0033222591362126247,
    "植田真梨恵": 0.0033222591362126247,
    "-inai-": 0.0033222591362126247,
    "BEYOND": 0.0033222591362126247,
    "ClariS": 0.0033222591362126247,
    "HarryP": 0.0033222591362126247,
    "Metrik": 0.0033222591362126247,
    "ウォルピス社": 0.0033222591362126247,
    "ついなちゃん": 0.0033222591362126247,
    "北大力南逸峰": 0.0033222591362126247,
    "小鳥遊めぐみ": 0.0033222591362126247,
    "里奈Rina": 0.0033222591362126247,
    "Ava Max": 0.0033222591362126247,
    "Loituma": 0.0033222591362126247,
    "SadSvit": 0.0033222591362126247,
    "Synth V": 0.0033222591362126247,
    "YOASOBI": 0.0033222591362126247,
    "いきものがかり": 0.0033222591362126247,
    "ユリイ・カノン": 0.0033222591362126247,
    "聖地亞戈合唱團": 0.0033222591362126247,
    "Big Sean": 0.0033222591362126247,
    "Kalafina": 0.0033222591362126247,
    "King Gnu": 0.0033222591362126247,
    "Santiano": 0.0033222591362126247,
    "TCHaruru": 0.0033222591362126247,
    "Westlife": 0.0033222591362126247,
    "АнимациЯ": 0.0033222591362126247,
    "初音ミクDark": 0.0033222591362126247,
    "FreeTempo": 0.0033222591362126247,
    "Mayday五月天": 0.0033222591362126247,
    "MyGO!!!!!": 0.0033222591362126247,
    "Synthesia": 0.0033222591362126247,
    "イヌクワチャンネル": 0.0033222591362126247,
    "神聖かまってちゃん": 0.0033222591362126247,
    "Herms Niel": 0.0033222591362126247,
    "Johann JEG": 0.0033222591362126247,
    "Juha Rossi": 0.0033222591362126247,
    "Marshmello": 0.0033222591362126247,
    "Tom Paxton": 0.0033222591362126247,
    "初音ミクAppend": 0.0033222591362126247,
    "Marin Hoxha": 0.0033222591362126247,
    "Rizky Ayuba": 0.0033222591362126247,
    "Janne Da Arc": 0.0033222591362126247,
    "Jeick Abrego": 0.0033222591362126247,
    "Tymko Padura": 0.0033222591362126247,
    "Дан. Покрасс": 0.0033222591362126247,
    "兄弟本色 G.U.T.S": 0.0033222591362126247,
    "滅火器 Fire EX.": 0.0033222591362126247,
    "Avril Lavigne": 0.0033222591362126247,
    "Eino Kettunen": 0.0033222591362126247,
    "Maksim Mrvica": 0.0033222591362126247,
    "Secret Garden": 0.0033222591362126247,
    "Loving Caliber": 0.0033222591362126247,
    "MY FIRST STORY": 0.0033222591362126247,
    "strike witches": 0.0033222591362126247,
    "小飛鼠Amelia Khor": 0.0033222591362126247,
    "Jean-Marc Natel": 0.0033222591362126247,
    "楊千嬅 Miriam Yeung": 0.0033222591362126247,
    "Διονύσιος Σολωμός": 0.0033222591362126247,
    "美秀集團 Amazing Show": 0.0033222591362126247,
    "Σταμάτης Σπανουδάκης": 0.0033222591362126247,
    "Hoffmann von Fallersleben": 0.0033222591362126247,
    "Ludoviko Lazaro Zamenhofo": 0.0033222591362126247,
    "Матве́й Исаа́кович Бла́нтер": 0.0033222591362126247,
    "total": 1
  }
}